{
  "@class" : "org.sehkah.ddon.tools.extractor.common.logic.resource.entity.tutorial_guide.TutorialDialogMessage",
  "CategoryGmdIdx" : 619,
  "FileHeader" : {
    "MagicBytesLength" : 4,
    "MagicString" : "TDM\u0000",
    "VersionBytesLength" : 4,
    "VersionNumber" : 2
  },
  "FileSize" : 36,
  "PageInfo" : [ {
    "@class" : "org.sehkah.ddon.tools.extractor.common.logic.resource.entity.tutorial_guide.TutorialDialogMessageDialogPage",
    "ImageId" : 415,
    "Message" : "Undercover Investigation is a mission to\ninfiltrate <NPC 681> the Marquis's inner circle\nand gather information that can be used during\ninterrogation, as well as to investigate the\nMarquis's words and actions.\n<COL ffdc78>※During the mission, Rift Teleport\ncannot be used.\nMoving to a different location via Rift Teleport\nwill result in going out of the mission area and\nfailing the quest.</COL>",
    "TextGmdIdx" : 0
  }, {
    "@class" : "org.sehkah.ddon.tools.extractor.common.logic.resource.entity.tutorial_guide.TutorialDialogMessageDialogPage",
    "ImageId" : 423,
    "Message" : "Also, the actions taken during this mission may\nhave an impact on \"Intelligence Assessment\".\n<COL ffdc78>When the announcement appears, let's\npay attention to the Chat Log</COL>.",
    "TextGmdIdx" : 1
  } ],
  "TitleGmdIdx" : 412,
  "TutorialTitleName" : "About \"Undercover\""
}