{
  "@class" : "org.sehkah.ddon.tools.extractor.lib.logic.entity.Archive",
  "fileHeader" : {
    "magicString" : "ARCC",
    "magicBytesLength" : 4,
    "versionNumber" : 7,
    "versionBytesLength" : 2
  },
  "resourceNum" : 3,
  "resource" : [ {
    "Path" : "scr\\st0100\\etc\\st0100_46m08n_t95",
    "PathCRC" : 156288658,
    "ResourceId" : 1526771899341784722,
    "Type" : 355479284,
    "TypeName" : "rLayout",
    "TypeExtension" : ".lot",
    "DataSize" : 256,
    "OriginalSize" : 1046,
    "Quality" : 2,
    "QualityName" : "QUALITY_DEFAULT",
    "Offset" : 32768
  }, {
    "Path" : "scr\\st0100\\etc\\st0100_46m08n_t97",
    "PathCRC" : 3881740222,
    "ResourceId" : 1526771903067236286,
    "Type" : 355479284,
    "TypeName" : "rLayout",
    "TypeExtension" : ".lot",
    "DataSize" : 120,
    "OriginalSize" : 358,
    "Quality" : 2,
    "QualityName" : "QUALITY_DEFAULT",
    "Offset" : 33024
  }, {
    "Path" : "scr\\st0100\\etc\\st0100_46m08n_p262",
    "PathCRC" : 2126895195,
    "ResourceId" : 1526771901312391259,
    "Type" : 355479284,
    "TypeName" : "rLayout",
    "TypeExtension" : ".lot",
    "DataSize" : 136,
    "OriginalSize" : 427,
    "Quality" : 2,
    "QualityName" : "QUALITY_DEFAULT",
    "Offset" : 33144
  } ],
  "fileSize" : 33280
}