{
  "@class" : "org.sehkah.ddon.tools.extractor.common.logic.resource.entity.Archive",
  "FileHeader" : {
    "MagicBytesLength" : 4,
    "MagicString" : "ARCC",
    "VersionBytesLength" : 2,
    "VersionNumber" : 7
  },
  "FileSize" : 2319624,
  "Resource" : [ {
    "@class" : "org.sehkah.ddon.tools.extractor.common.logic.resource.entity.ResourceInfo",
    "DataSize" : 708344,
    "Offset" : 32768,
    "OriginalSize" : 1398168,
    "Path" : "obj\\om\\om507240\\model\\om507244_00_NM",
    "PathCRC" : 4098553607,
    "Quality" : 2,
    "QualityName" : "QUALITY_DEFAULT",
    "ResourceId" : 2602902377640687367,
    "Type" : 606035435,
    "TypeExtension" : ".tex",
    "TypeName" : "rTexture"
  }, {
    "@class" : "org.sehkah.ddon.tools.extractor.common.logic.resource.entity.ResourceInfo",
    "DataSize" : 496528,
    "Offset" : 741112,
    "OriginalSize" : 699112,
    "Path" : "obj\\om\\om507240\\model\\om507244_00_BM",
    "PathCRC" : 1493153803,
    "Quality" : 2,
    "QualityName" : "QUALITY_DEFAULT",
    "ResourceId" : 2602902375035287563,
    "Type" : 606035435,
    "TypeExtension" : ".tex",
    "TypeName" : "rTexture"
  }, {
    "@class" : "org.sehkah.ddon.tools.extractor.common.logic.resource.entity.ResourceInfo",
    "DataSize" : 74424,
    "Offset" : 1237640,
    "OriginalSize" : 87476,
    "Path" : "obj\\om\\om507240\\model\\om507241_03_NM",
    "PathCRC" : 3032971086,
    "Quality" : 2,
    "QualityName" : "QUALITY_DEFAULT",
    "ResourceId" : 2602902376575104846,
    "Type" : 606035435,
    "TypeExtension" : ".tex",
    "TypeName" : "rTexture"
  }, {
    "@class" : "org.sehkah.ddon.tools.extractor.common.logic.resource.entity.ResourceInfo",
    "DataSize" : 32744,
    "Offset" : 1312064,
    "OriginalSize" : 43764,
    "Path" : "obj\\om\\om507240\\model\\om507241_03_BM",
    "PathCRC" : 410138690,
    "Quality" : 2,
    "QualityName" : "QUALITY_DEFAULT",
    "ResourceId" : 2602902373952272450,
    "Type" : 606035435,
    "TypeExtension" : ".tex",
    "TypeName" : "rTexture"
  }, {
    "@class" : "org.sehkah.ddon.tools.extractor.common.logic.resource.entity.ResourceInfo",
    "DataSize" : 610424,
    "Offset" : 1344808,
    "OriginalSize" : 699128,
    "Path" : "obj\\om\\om507240\\model\\om507240_01_NM",
    "PathCRC" : 3099178097,
    "Quality" : 2,
    "QualityName" : "QUALITY_DEFAULT",
    "ResourceId" : 2602902376641311857,
    "Type" : 606035435,
    "TypeExtension" : ".tex",
    "TypeName" : "rTexture"
  }, {
    "@class" : "org.sehkah.ddon.tools.extractor.common.logic.resource.entity.ResourceInfo",
    "DataSize" : 268336,
    "Offset" : 1955232,
    "OriginalSize" : 349592,
    "Path" : "obj\\om\\om507240\\model\\om507240_01_BM",
    "PathCRC" : 336395133,
    "Quality" : 2,
    "QualityName" : "QUALITY_DEFAULT",
    "ResourceId" : 2602902373878528893,
    "Type" : 606035435,
    "TypeExtension" : ".tex",
    "TypeName" : "rTexture"
  }, {
    "@class" : "org.sehkah.ddon.tools.extractor.common.logic.resource.entity.ResourceInfo",
    "DataSize" : 664,
    "Offset" : 2223568,
    "OriginalSize" : 5520,
    "Path" : "obj\\om\\om507240\\model\\om507240",
    "PathCRC" : 801864086,
    "Quality" : 2,
    "QualityName" : "QUALITY_DEFAULT",
    "ResourceId" : 2831014465460992406,
    "Type" : 659146920,
    "TypeExtension" : ".mrl",
    "TypeName" : "rMaterial"
  }, {
    "@class" : "org.sehkah.ddon.tools.extractor.common.logic.resource.entity.ResourceInfo",
    "DataSize" : 83696,
    "Offset" : 2224232,
    "OriginalSize" : 154224,
    "Path" : "obj\\om\\om507240\\model\\om507240",
    "PathCRC" : 801864086,
    "Quality" : 2,
    "QualityName" : "QUALITY_DEFAULT",
    "ResourceId" : 6386482873780369814,
    "Type" : 1486968918,
    "TypeExtension" : ".mod",
    "TypeName" : "rModel"
  }, {
    "@class" : "org.sehkah.ddon.tools.extractor.common.logic.resource.entity.ResourceInfo",
    "DataSize" : 1408,
    "Offset" : 2307928,
    "OriginalSize" : 3590,
    "Path" : "obj\\om\\om507240\\collision\\om507240_h00",
    "PathCRC" : 3083181204,
    "Quality" : 2,
    "QualityName" : "QUALITY_DEFAULT",
    "ResourceId" : 5907728339069934740,
    "Type" : 1375500191,
    "TypeExtension" : ".sbc",
    "TypeName" : "rCollision"
  }, {
    "@class" : "org.sehkah.ddon.tools.extractor.common.logic.resource.entity.ResourceInfo",
    "DataSize" : 10288,
    "Offset" : 2309336,
    "OriginalSize" : 22596,
    "Path" : "obj\\om\\om507240\\collision\\om507240_e00",
    "PathCRC" : 3206352839,
    "Quality" : 2,
    "QualityName" : "QUALITY_DEFAULT",
    "ResourceId" : 5907728339193106375,
    "Type" : 1375500191,
    "TypeExtension" : ".sbc",
    "TypeName" : "rCollision"
  } ],
  "ResourceNum" : 10
}