{
  "@class" : "org.sehkah.ddon.tools.extractor.lib.logic.entity.Archive",
  "fileHeader" : {
    "magicString" : "ARCC",
    "magicBytesLength" : 4,
    "versionNumber" : 7,
    "versionBytesLength" : 2
  },
  "resourceNum" : 5,
  "resource" : [ {
    "Path" : "param\\hmem\\edit\\01\\hmem_m_04",
    "PathCRC" : 1483276896,
    "ResourceId" : 4506220757200208480,
    "Type" : 1049186279,
    "TypeName" : "rCharacterEdit",
    "TypeExtension" : ".edt",
    "DataSize" : 448,
    "OriginalSize" : 983,
    "Quality" : 2,
    "QualityName" : "QUALITY_DEFAULT",
    "Offset" : 32768
  }, {
    "Path" : "param\\hmem\\edit\\01\\hmem_m_05",
    "PathCRC" : 795751158,
    "ResourceId" : 4506220756512682742,
    "Type" : 1049186279,
    "TypeName" : "rCharacterEdit",
    "TypeExtension" : ".edt",
    "DataSize" : 408,
    "OriginalSize" : 983,
    "Quality" : 2,
    "QualityName" : "QUALITY_DEFAULT",
    "Offset" : 33216
  }, {
    "Path" : "param\\hmem\\edit\\01\\hmem_m_01",
    "PathCRC" : 671348463,
    "ResourceId" : 4506220756388280047,
    "Type" : 1049186279,
    "TypeName" : "rCharacterEdit",
    "TypeExtension" : ".edt",
    "DataSize" : 400,
    "OriginalSize" : 983,
    "Quality" : 2,
    "QualityName" : "QUALITY_DEFAULT",
    "Offset" : 33624
  }, {
    "Path" : "param\\hmem\\edit\\01\\hmem_m_02",
    "PathCRC" : 2970265429,
    "ResourceId" : 4506220758687197013,
    "Type" : 1049186279,
    "TypeName" : "rCharacterEdit",
    "TypeExtension" : ".edt",
    "DataSize" : 400,
    "OriginalSize" : 983,
    "Quality" : 2,
    "QualityName" : "QUALITY_DEFAULT",
    "Offset" : 34024
  }, {
    "Path" : "param\\hmem\\edit\\01\\hmem_m_03",
    "PathCRC" : 3322779587,
    "ResourceId" : 4506220759039711171,
    "Type" : 1049186279,
    "TypeName" : "rCharacterEdit",
    "TypeExtension" : ".edt",
    "DataSize" : 400,
    "OriginalSize" : 983,
    "Quality" : 2,
    "QualityName" : "QUALITY_DEFAULT",
    "Offset" : 34424
  } ],
  "fileSize" : 34824
}