{
  "@class" : "org.sehkah.ddon.tools.extractor.lib.logic.resource.entity.season2.stage.Layout",
  "FileHeader" : {
    "MagicString" : "lot\u0000",
    "MagicBytesLength" : 4,
    "VersionNumber" : 117,
    "VersionBytesLength" : 4
  },
  "Array" : [ {
    "ID" : 0,
    "Type" : 0,
    "TypeName" : "SetInfoOm",
    "Info" : {
      "AreaMasterNo" : 0,
      "AreaReleaseNo" : 0,
      "AreaReleaseOFF" : false,
      "AreaReleaseON" : false,
      "BreakGroup" : 0,
      "BreakID" : 0,
      "BreakKind" : 3,
      "DisableEffect" : false,
      "DisableOnlyEffect" : false,
      "EnableSyncLight" : false,
      "EnableZone" : true,
      "InfoCoord" : {
        "Name" : "om522600",
        "UnitID" : 522600,
        "Position" : {
          "X" : 6125.6978,
          "Y" : -499.99994,
          "Z" : -22332.273
        },
        "Angle" : {
          "X" : -0.0,
          "Y" : -2.134788,
          "Z" : 0.0
        },
        "Scale" : {
          "X" : 1.25,
          "Y" : 1.25,
          "Z" : 1.25
        },
        "AreaHitNo" : -1
      },
      "InitMtnNo" : 0,
      "IsBreakLink" : false,
      "IsBreakQuest" : false,
      "IsMyQuest" : false,
      "IsNoSbc" : false,
      "KeyNo" : 0,
      "OpenFlag" : false,
      "QuestFlag" : 0,
      "WarpPointId" : 0
    }
  }, {
    "ID" : 1,
    "Type" : 0,
    "TypeName" : "SetInfoOm",
    "Info" : {
      "AreaMasterNo" : 0,
      "AreaReleaseNo" : 0,
      "AreaReleaseOFF" : false,
      "AreaReleaseON" : false,
      "BreakGroup" : 0,
      "BreakID" : 0,
      "BreakKind" : 3,
      "DisableEffect" : false,
      "DisableOnlyEffect" : false,
      "EnableSyncLight" : false,
      "EnableZone" : true,
      "InfoCoord" : {
        "Name" : "om522601",
        "UnitID" : 522601,
        "Position" : {
          "X" : 5884.126,
          "Y" : -500.0,
          "Z" : -22220.902
        },
        "Angle" : {
          "X" : -0.0,
          "Y" : -0.900616,
          "Z" : 0.0
        },
        "Scale" : {
          "X" : 1.25,
          "Y" : 1.25,
          "Z" : 1.25
        },
        "AreaHitNo" : -1
      },
      "InitMtnNo" : 0,
      "IsBreakLink" : false,
      "IsBreakQuest" : false,
      "IsMyQuest" : false,
      "IsNoSbc" : false,
      "KeyNo" : 0,
      "OpenFlag" : false,
      "QuestFlag" : 0,
      "WarpPointId" : 0
    }
  }, {
    "ID" : 2,
    "Type" : 0,
    "TypeName" : "SetInfoOm",
    "Info" : {
      "AreaMasterNo" : 0,
      "AreaReleaseNo" : 0,
      "AreaReleaseOFF" : false,
      "AreaReleaseON" : false,
      "BreakGroup" : 0,
      "BreakID" : 0,
      "BreakKind" : 3,
      "DisableEffect" : false,
      "DisableOnlyEffect" : false,
      "EnableSyncLight" : false,
      "EnableZone" : true,
      "InfoCoord" : {
        "Name" : "om522602",
        "UnitID" : 522602,
        "Position" : {
          "X" : 4188.2026,
          "Y" : -356.02136,
          "Z" : -23174.777
        },
        "Angle" : {
          "X" : -0.0,
          "Y" : -1.110765,
          "Z" : 0.0
        },
        "Scale" : {
          "X" : 1.0,
          "Y" : 1.0,
          "Z" : 1.0
        },
        "AreaHitNo" : -1
      },
      "InitMtnNo" : 0,
      "IsBreakLink" : false,
      "IsBreakQuest" : false,
      "IsMyQuest" : false,
      "IsNoSbc" : false,
      "KeyNo" : 0,
      "OpenFlag" : false,
      "QuestFlag" : 0,
      "WarpPointId" : 0
    }
  }, {
    "ID" : 3,
    "Type" : 0,
    "TypeName" : "SetInfoOm",
    "Info" : {
      "AreaMasterNo" : 0,
      "AreaReleaseNo" : 0,
      "AreaReleaseOFF" : false,
      "AreaReleaseON" : false,
      "BreakGroup" : 0,
      "BreakID" : 0,
      "BreakKind" : 3,
      "DisableEffect" : false,
      "DisableOnlyEffect" : false,
      "EnableSyncLight" : false,
      "EnableZone" : true,
      "InfoCoord" : {
        "Name" : "om522603",
        "UnitID" : 522603,
        "Position" : {
          "X" : 6191.65,
          "Y" : -500.00003,
          "Z" : -22120.178
        },
        "Angle" : {
          "X" : -0.0,
          "Y" : 1.589315,
          "Z" : 0.0
        },
        "Scale" : {
          "X" : 1.25,
          "Y" : 1.25,
          "Z" : 1.25
        },
        "AreaHitNo" : -1
      },
      "InitMtnNo" : 0,
      "IsBreakLink" : false,
      "IsBreakQuest" : false,
      "IsMyQuest" : false,
      "IsNoSbc" : false,
      "KeyNo" : 0,
      "OpenFlag" : false,
      "QuestFlag" : 0,
      "WarpPointId" : 0
    }
  }, {
    "ID" : 4,
    "Type" : 0,
    "TypeName" : "SetInfoOm",
    "Info" : {
      "AreaMasterNo" : 0,
      "AreaReleaseNo" : 0,
      "AreaReleaseOFF" : false,
      "AreaReleaseON" : false,
      "BreakGroup" : 0,
      "BreakID" : 0,
      "BreakKind" : 3,
      "DisableEffect" : false,
      "DisableOnlyEffect" : false,
      "EnableSyncLight" : false,
      "EnableZone" : true,
      "InfoCoord" : {
        "Name" : "om522443",
        "UnitID" : 522443,
        "Position" : {
          "X" : 5725.7544,
          "Y" : -500.0,
          "Z" : -23594.947
        },
        "Angle" : {
          "X" : -0.0,
          "Y" : 0.965005,
          "Z" : 0.0
        },
        "Scale" : {
          "X" : 1.25,
          "Y" : 1.25,
          "Z" : 1.25
        },
        "AreaHitNo" : -1
      },
      "InitMtnNo" : 0,
      "IsBreakLink" : false,
      "IsBreakQuest" : false,
      "IsMyQuest" : false,
      "IsNoSbc" : false,
      "KeyNo" : 0,
      "OpenFlag" : false,
      "QuestFlag" : 0,
      "WarpPointId" : 0
    }
  }, {
    "ID" : 5,
    "Type" : 0,
    "TypeName" : "SetInfoOm",
    "Info" : {
      "AreaMasterNo" : 0,
      "AreaReleaseNo" : 0,
      "AreaReleaseOFF" : false,
      "AreaReleaseON" : false,
      "BreakGroup" : 0,
      "BreakID" : 0,
      "BreakKind" : 3,
      "DisableEffect" : false,
      "DisableOnlyEffect" : false,
      "EnableSyncLight" : false,
      "EnableZone" : true,
      "InfoCoord" : {
        "Name" : "om522441",
        "UnitID" : 522441,
        "Position" : {
          "X" : 5820.811,
          "Y" : -499.99997,
          "Z" : -23732.072
        },
        "Angle" : {
          "X" : -0.0,
          "Y" : 1.973693,
          "Z" : 0.0
        },
        "Scale" : {
          "X" : 1.0,
          "Y" : 1.0,
          "Z" : 1.0
        },
        "AreaHitNo" : -1
      },
      "InitMtnNo" : 0,
      "IsBreakLink" : false,
      "IsBreakQuest" : false,
      "IsMyQuest" : false,
      "IsNoSbc" : false,
      "KeyNo" : 0,
      "OpenFlag" : false,
      "QuestFlag" : 0,
      "WarpPointId" : 0
    }
  }, {
    "ID" : 6,
    "Type" : 0,
    "TypeName" : "SetInfoOm",
    "Info" : {
      "AreaMasterNo" : 0,
      "AreaReleaseNo" : 0,
      "AreaReleaseOFF" : false,
      "AreaReleaseON" : false,
      "BreakGroup" : 0,
      "BreakID" : 0,
      "BreakKind" : 3,
      "DisableEffect" : false,
      "DisableOnlyEffect" : false,
      "EnableSyncLight" : false,
      "EnableZone" : true,
      "InfoCoord" : {
        "Name" : "om522604",
        "UnitID" : 522604,
        "Position" : {
          "X" : 5095.3965,
          "Y" : -500.0,
          "Z" : -23705.072
        },
        "Angle" : {
          "X" : -0.0,
          "Y" : 2.809949,
          "Z" : 0.0
        },
        "Scale" : {
          "X" : 1.25,
          "Y" : 1.25,
          "Z" : 1.25
        },
        "AreaHitNo" : -1
      },
      "InitMtnNo" : 0,
      "IsBreakLink" : false,
      "IsBreakQuest" : false,
      "IsMyQuest" : false,
      "IsNoSbc" : false,
      "KeyNo" : 0,
      "OpenFlag" : false,
      "QuestFlag" : 0,
      "WarpPointId" : 0
    }
  }, {
    "ID" : 7,
    "Type" : 0,
    "TypeName" : "SetInfoOm",
    "Info" : {
      "AreaMasterNo" : 0,
      "AreaReleaseNo" : 0,
      "AreaReleaseOFF" : false,
      "AreaReleaseON" : false,
      "BreakGroup" : 0,
      "BreakID" : 0,
      "BreakKind" : 3,
      "DisableEffect" : false,
      "DisableOnlyEffect" : false,
      "EnableSyncLight" : false,
      "EnableZone" : true,
      "InfoCoord" : {
        "Name" : "om522602",
        "UnitID" : 522602,
        "Position" : {
          "X" : 6125.061,
          "Y" : -473.12497,
          "Z" : -22080.65
        },
        "Angle" : {
          "X" : 0.271073,
          "Y" : -0.911181,
          "Z" : 0.059227
        },
        "Scale" : {
          "X" : 1.25,
          "Y" : 1.25,
          "Z" : 1.25
        },
        "AreaHitNo" : -1
      },
      "InitMtnNo" : 0,
      "IsBreakLink" : false,
      "IsBreakQuest" : false,
      "IsMyQuest" : false,
      "IsNoSbc" : false,
      "KeyNo" : 0,
      "OpenFlag" : false,
      "QuestFlag" : 0,
      "WarpPointId" : 0
    }
  }, {
    "ID" : 8,
    "Type" : 0,
    "TypeName" : "SetInfoOm",
    "Info" : {
      "AreaMasterNo" : 0,
      "AreaReleaseNo" : 0,
      "AreaReleaseOFF" : false,
      "AreaReleaseON" : false,
      "BreakGroup" : 0,
      "BreakID" : 0,
      "BreakKind" : 3,
      "DisableEffect" : false,
      "DisableOnlyEffect" : false,
      "EnableSyncLight" : false,
      "EnableZone" : true,
      "InfoCoord" : {
        "Name" : "om522602",
        "UnitID" : 522602,
        "Position" : {
          "X" : 6954.0415,
          "Y" : -500.00003,
          "Z" : -23445.31
        },
        "Angle" : {
          "X" : -0.0,
          "Y" : -0.946536,
          "Z" : 0.0
        },
        "Scale" : {
          "X" : 1.25,
          "Y" : 1.25,
          "Z" : 1.25
        },
        "AreaHitNo" : -1
      },
      "InitMtnNo" : 0,
      "IsBreakLink" : false,
      "IsBreakQuest" : false,
      "IsMyQuest" : false,
      "IsNoSbc" : false,
      "KeyNo" : 0,
      "OpenFlag" : false,
      "QuestFlag" : 0,
      "WarpPointId" : 0
    }
  }, {
    "ID" : 9,
    "Type" : 0,
    "TypeName" : "SetInfoOm",
    "Info" : {
      "AreaMasterNo" : 0,
      "AreaReleaseNo" : 0,
      "AreaReleaseOFF" : false,
      "AreaReleaseON" : false,
      "BreakGroup" : 0,
      "BreakID" : 0,
      "BreakKind" : 3,
      "DisableEffect" : false,
      "DisableOnlyEffect" : false,
      "EnableSyncLight" : false,
      "EnableZone" : true,
      "InfoCoord" : {
        "Name" : "om522603",
        "UnitID" : 522603,
        "Position" : {
          "X" : 3278.6492,
          "Y" : -354.67676,
          "Z" : -23461.03
        },
        "Angle" : {
          "X" : -0.0,
          "Y" : -0.515585,
          "Z" : 0.0
        },
        "Scale" : {
          "X" : 1.25,
          "Y" : 1.25,
          "Z" : 1.25
        },
        "AreaHitNo" : -1
      },
      "InitMtnNo" : 0,
      "IsBreakLink" : false,
      "IsBreakQuest" : false,
      "IsMyQuest" : false,
      "IsNoSbc" : false,
      "KeyNo" : 0,
      "OpenFlag" : false,
      "QuestFlag" : 0,
      "WarpPointId" : 0
    }
  }, {
    "ID" : 10,
    "Type" : 0,
    "TypeName" : "SetInfoOm",
    "Info" : {
      "AreaMasterNo" : 0,
      "AreaReleaseNo" : 0,
      "AreaReleaseOFF" : false,
      "AreaReleaseON" : false,
      "BreakGroup" : 0,
      "BreakID" : 0,
      "BreakKind" : 3,
      "DisableEffect" : false,
      "DisableOnlyEffect" : false,
      "EnableSyncLight" : false,
      "EnableZone" : true,
      "InfoCoord" : {
        "Name" : "om522443",
        "UnitID" : 522443,
        "Position" : {
          "X" : 4306.175,
          "Y" : -358.23892,
          "Z" : -23338.68
        },
        "Angle" : {
          "X" : -0.0,
          "Y" : 0.953956,
          "Z" : 0.0
        },
        "Scale" : {
          "X" : 1.25,
          "Y" : 1.25,
          "Z" : 1.25
        },
        "AreaHitNo" : -1
      },
      "InitMtnNo" : 0,
      "IsBreakLink" : false,
      "IsBreakQuest" : false,
      "IsMyQuest" : false,
      "IsNoSbc" : false,
      "KeyNo" : 0,
      "OpenFlag" : false,
      "QuestFlag" : 0,
      "WarpPointId" : 0
    }
  }, {
    "ID" : 11,
    "Type" : 0,
    "TypeName" : "SetInfoOm",
    "Info" : {
      "AreaMasterNo" : 0,
      "AreaReleaseNo" : 0,
      "AreaReleaseOFF" : false,
      "AreaReleaseON" : false,
      "BreakGroup" : 0,
      "BreakID" : 0,
      "BreakKind" : 3,
      "DisableEffect" : false,
      "DisableOnlyEffect" : false,
      "EnableSyncLight" : false,
      "EnableZone" : true,
      "InfoCoord" : {
        "Name" : "om522441",
        "UnitID" : 522441,
        "Position" : {
          "X" : 6104.912,
          "Y" : -500.0,
          "Z" : -22163.357
        },
        "Angle" : {
          "X" : -0.0,
          "Y" : 0.465372,
          "Z" : 0.0
        },
        "Scale" : {
          "X" : 1.25,
          "Y" : 1.25,
          "Z" : 1.25
        },
        "AreaHitNo" : -1
      },
      "InitMtnNo" : 0,
      "IsBreakLink" : false,
      "IsBreakQuest" : false,
      "IsMyQuest" : false,
      "IsNoSbc" : false,
      "KeyNo" : 0,
      "OpenFlag" : false,
      "QuestFlag" : 0,
      "WarpPointId" : 0
    }
  }, {
    "ID" : 12,
    "Type" : 0,
    "TypeName" : "SetInfoOm",
    "Info" : {
      "AreaMasterNo" : 0,
      "AreaReleaseNo" : 0,
      "AreaReleaseOFF" : false,
      "AreaReleaseON" : false,
      "BreakGroup" : 0,
      "BreakID" : 0,
      "BreakKind" : 3,
      "DisableEffect" : false,
      "DisableOnlyEffect" : false,
      "EnableSyncLight" : false,
      "EnableZone" : true,
      "InfoCoord" : {
        "Name" : "om520130",
        "UnitID" : 520130,
        "Position" : {
          "X" : 4503.3066,
          "Y" : 1098.7975,
          "Z" : -18493.049
        },
        "Angle" : {
          "X" : -0.051957,
          "Y" : 0.971645,
          "Z" : 0.0
        },
        "Scale" : {
          "X" : 1.0,
          "Y" : 1.0,
          "Z" : 1.0
        },
        "AreaHitNo" : -1
      },
      "InitMtnNo" : 0,
      "IsBreakLink" : false,
      "IsBreakQuest" : false,
      "IsMyQuest" : false,
      "IsNoSbc" : false,
      "KeyNo" : 0,
      "OpenFlag" : false,
      "QuestFlag" : 0,
      "WarpPointId" : 0
    }
  }, {
    "ID" : 13,
    "Type" : 0,
    "TypeName" : "SetInfoOm",
    "Info" : {
      "AreaMasterNo" : 0,
      "AreaReleaseNo" : 0,
      "AreaReleaseOFF" : false,
      "AreaReleaseON" : false,
      "BreakGroup" : 0,
      "BreakID" : 0,
      "BreakKind" : 3,
      "DisableEffect" : false,
      "DisableOnlyEffect" : false,
      "EnableSyncLight" : false,
      "EnableZone" : true,
      "InfoCoord" : {
        "Name" : "om522600",
        "UnitID" : 522600,
        "Position" : {
          "X" : 6766.9453,
          "Y" : -499.99997,
          "Z" : -23343.941
        },
        "Angle" : {
          "X" : -0.0,
          "Y" : -2.134788,
          "Z" : 0.0
        },
        "Scale" : {
          "X" : 1.25,
          "Y" : 1.25,
          "Z" : 1.25
        },
        "AreaHitNo" : -1
      },
      "InitMtnNo" : 0,
      "IsBreakLink" : false,
      "IsBreakQuest" : false,
      "IsMyQuest" : false,
      "IsNoSbc" : false,
      "KeyNo" : 0,
      "OpenFlag" : false,
      "QuestFlag" : 0,
      "WarpPointId" : 0
    }
  }, {
    "ID" : 14,
    "Type" : 0,
    "TypeName" : "SetInfoOm",
    "Info" : {
      "AreaMasterNo" : 0,
      "AreaReleaseNo" : 0,
      "AreaReleaseOFF" : false,
      "AreaReleaseON" : false,
      "BreakGroup" : 0,
      "BreakID" : 0,
      "BreakKind" : 3,
      "DisableEffect" : false,
      "DisableOnlyEffect" : false,
      "EnableSyncLight" : false,
      "EnableZone" : true,
      "InfoCoord" : {
        "Name" : "om522601",
        "UnitID" : 522601,
        "Position" : {
          "X" : 6855.6167,
          "Y" : -500.0,
          "Z" : -23127.271
        },
        "Angle" : {
          "X" : -0.0,
          "Y" : -0.203696,
          "Z" : 0.0
        },
        "Scale" : {
          "X" : 1.25,
          "Y" : 1.25,
          "Z" : 1.25
        },
        "AreaHitNo" : -1
      },
      "InitMtnNo" : 0,
      "IsBreakLink" : false,
      "IsBreakQuest" : false,
      "IsMyQuest" : false,
      "IsNoSbc" : false,
      "KeyNo" : 0,
      "OpenFlag" : false,
      "QuestFlag" : 0,
      "WarpPointId" : 0
    }
  }, {
    "ID" : 15,
    "Type" : 0,
    "TypeName" : "SetInfoOm",
    "Info" : {
      "AreaMasterNo" : 0,
      "AreaReleaseNo" : 0,
      "AreaReleaseOFF" : false,
      "AreaReleaseON" : false,
      "BreakGroup" : 0,
      "BreakID" : 0,
      "BreakKind" : 3,
      "DisableEffect" : false,
      "DisableOnlyEffect" : false,
      "EnableSyncLight" : false,
      "EnableZone" : true,
      "InfoCoord" : {
        "Name" : "om522442",
        "UnitID" : 522442,
        "Position" : {
          "X" : 6695.214,
          "Y" : -499.99997,
          "Z" : -23202.479
        },
        "Angle" : {
          "X" : -0.0,
          "Y" : 1.35781,
          "Z" : 0.0
        },
        "Scale" : {
          "X" : 1.0,
          "Y" : 1.0,
          "Z" : 1.0
        },
        "AreaHitNo" : -1
      },
      "InitMtnNo" : 0,
      "IsBreakLink" : false,
      "IsBreakQuest" : false,
      "IsMyQuest" : false,
      "IsNoSbc" : false,
      "KeyNo" : 0,
      "OpenFlag" : false,
      "QuestFlag" : 0,
      "WarpPointId" : 0
    }
  }, {
    "ID" : 16,
    "Type" : 0,
    "TypeName" : "SetInfoOm",
    "Info" : {
      "AreaMasterNo" : 0,
      "AreaReleaseNo" : 0,
      "AreaReleaseOFF" : false,
      "AreaReleaseON" : false,
      "BreakGroup" : 0,
      "BreakID" : 0,
      "BreakKind" : 3,
      "DisableEffect" : false,
      "DisableOnlyEffect" : false,
      "EnableSyncLight" : false,
      "EnableZone" : true,
      "InfoCoord" : {
        "Name" : "om522604",
        "UnitID" : 522604,
        "Position" : {
          "X" : 6470.7573,
          "Y" : -545.4332,
          "Z" : -21658.791
        },
        "Angle" : {
          "X" : -0.901416,
          "Y" : 1.673356,
          "Z" : 0.151041
        },
        "Scale" : {
          "X" : 1.25,
          "Y" : 1.25,
          "Z" : 1.25
        },
        "AreaHitNo" : -1
      },
      "InitMtnNo" : 0,
      "IsBreakLink" : false,
      "IsBreakQuest" : false,
      "IsMyQuest" : false,
      "IsNoSbc" : false,
      "KeyNo" : 0,
      "OpenFlag" : false,
      "QuestFlag" : 0,
      "WarpPointId" : 0
    }
  } ],
  "SetInfoNeedNums" : [ 0, 0, 0, 17, 0, 0, 0, 0, 0, 0, 0, 0, 0, 0, 0, 0, 0, 0, 0, 0, 0, 0 ],
  "FileSize" : 1800
}